Metadata-Version: 2.1
Name: phayes
Version: 0.1.0
Summary: Bayesian phase and amplitude estimation
Home-page: https://github.com/SamDuffield/bayesian-phase-estimation
Author: Sam Duffield
Author-email: sam.duffield@quantinuum.com
License: Apache 2
Platform: any
Classifier: Programming Language :: Python
Classifier: Intended Audience :: Developers
Classifier: Intended Audience :: Science/Research
Classifier: Topic :: Scientific/Engineering
Requires-Python: >=3.8
License-File: LICENSE
